Cities/__init__.py
Cities/cities_retriever.py
Cities/dict_builder.py
Cities/settings.py
Cities-1.1.dist-info/LICENSE.txt
Cities-1.1.dist-info/METADATA
Cities-1.1.dist-info/WHEEL
Cities-1.1.dist-info/top_level.txt
Cities-1.1.dist-info/RECORD
