Metadata-Version: 2.1
Name: Cities
Version: 1.1
Summary: Cities is a simple tool for searching cities located at a given longitude and latitude range.
Home-page: https://github.com/131250208/Cities
Author: Andy Wong
Author-email: wychengpublic@163.com
License: MIT
Platform: UNKNOWN
Classifier: License :: OSI Approved :: MIT License
Classifier: Programming Language :: Python
Classifier: Programming Language :: Python :: 3
Classifier: Programming Language :: Python :: 3.6
Classifier: Programming Language :: Python :: Implementation :: CPython
Classifier: Programming Language :: Python :: Implementation :: PyPy
Requires-Python: >=3.5.0
Requires-Dist: pyprind
Requires-Dist: numpy
